gcloud_config_helper/__init__.py
gcloud_config_helper/__main__.py
gcloud_config_helper/gcloud_config_helper.py
gcloud_config_helper-0.3.1.dist-info/LICENSE
gcloud_config_helper-0.3.1.dist-info/METADATA
gcloud_config_helper-0.3.1.dist-info/WHEEL
gcloud_config_helper-0.3.1.dist-info/top_level.txt
gcloud_config_helper-0.3.1.dist-info/RECORD
