Metadata-Version: 2.1
Name: gcloud-config-helper
Version: 0.3.1
Summary: obtain Google GCloud configuration credentials
Home-page: https://github.com/binxio/python-gcloud-config-helper
Author: Mark van Holsteijn
Author-email: markvanholsteijn@binx.io
License: Apache Software License 2.0
Keywords: gcloud_config_helper
Classifier: Development Status :: 2 - Pre-Alpha
Classifier: Intended Audience :: Developers
Classifier: License :: OSI Approved :: Apache Software License
Classifier: Natural Language :: English
Classifier: Programming Language :: Python :: 3
Classifier: Programming Language :: Python :: 3.5
Classifier: Programming Language :: Python :: 3.6
Classifier: Programming Language :: Python :: 3.7
Classifier: Programming Language :: Python :: 3.8
Classifier: Programming Language :: Python :: 3.9
Requires-Python: >=3.5
License-File: LICENSE
Requires-Dist: python-dateutil
Requires-Dist: google-auth
Requires-Dist: pytz
